inbreeding_calculator.py
inbreeding_calculator-1.0.1.dist-info/METADATA
inbreeding_calculator-1.0.1.dist-info/WHEEL
inbreeding_calculator-1.0.1.dist-info/licenses/LICENSE.md
inbreeding_calculator-1.0.1.dist-info/RECORD
