Metadata-Version: 2.3
Name: inbreeding_calculator
Version: 1.0.1
Summary: Calculate the inbreeding coefficient of a pedigree in Python.
Project-URL: Homepage, https://github.com/Owen-Dechow/inbreeding-python
Author-email: Owen Dechow <owen.dechow@gmail.com>
License: MIT
Classifier: Intended Audience :: Science/Research
Classifier: Operating System :: OS Independent
Classifier: Programming Language :: Python :: 3
Classifier: Topic :: Scientific/Engineering :: Bio-Informatics
Requires-Python: >=3.0
